atten_lstm/__init__.py
atten_lstm/_main.py
AttentionLSTM-0.1.dist-info/LICENCE
AttentionLSTM-0.1.dist-info/METADATA
AttentionLSTM-0.1.dist-info/WHEEL
AttentionLSTM-0.1.dist-info/top_level.txt
AttentionLSTM-0.1.dist-info/RECORD
